tradeX/__init__.py
tradeX/bots/AbnormalDetectionBot.py
tradeX/bots/BinanceDataBot.py
tradeX/bots/LiveAbnormalDetectionBot.py
tradeX/bots/LogOnlyBot.py
tradeX/bots/SimpleBot.py
tradeX/bots/__init__.py
tradeX/bots/binance_bot.py
tradeX/bots/consts.py
tradeX/datasets/BinanceDataset.py
tradeX/datasets/ClassifierDataset.py
tradeX/datasets/DirectionDataset.py
tradeX/datasets/RegressionDataset.py
tradeX/datasets/__init__.py
tradeX/datasets/consts.py
tradeX/models/BinaryClassifier.py
tradeX/models/DirectionModel.py
tradeX/models/EModel.py
tradeX/models/FC_LSTM.py
tradeX/models/RegressionModel.py
tradeX/models/SimpleMLPClassifier.py
tradeX/models/__init__.py
tradeX/models/lstm.py
tradeX/scripts/__init__.py
tradeX/scripts/get_all_time_data.py
tradeX/scripts/split_train_val.py
tradeX/utils/__init__.py
tradeX/utils/args.py
tradeX/utils/data.py
tradeX/utils/data_getter.py
tradeX/utils/evaluation.py
tradeX/utils/feature_engineering.py
tradeX/utils/losses.py
tradeX/utils/model.py
tradeX/utils/optimizer.py
tradeX/utils/time.py
tradeX-0.0.3.data/data/requirements.txt
webui/__init__.py
webui/stream_lit.py
tradeX-0.0.3.dist-info/LICENSE.txt
tradeX-0.0.3.dist-info/METADATA
tradeX-0.0.3.dist-info/WHEEL
tradeX-0.0.3.dist-info/top_level.txt
tradeX-0.0.3.dist-info/RECORD
