Metadata-Version: 2.1
Name: tradeX
Version: 0.0.3
Summary: Machine learning based crypto currency price prediction
Author: TaQuangTu
Author-email: taquangtu132@gmail.com
License: LICENSE
Classifier: Programming Language :: Python :: 3
Classifier: License :: OSI Approved :: MIT License
Classifier: Operating System :: OS Independent
License-File: LICENSE.txt
Requires-Dist: binance (==0.3)
Requires-Dist: loguru (==0.6.0)
Requires-Dist: matplotlib (==3.6.0)
Requires-Dist: numpy (==1.23.4)
Requires-Dist: Pillow (==9.3.0)
Requires-Dist: plotly (==5.13.0)
Requires-Dist: python-binance (==1.0.15)
Requires-Dist: pytorch-lightning (==1.7.7)
Requires-Dist: regex (==2022.3.2)
Requires-Dist: requests (==2.28.1)
Requires-Dist: tacv
Requires-Dist: torch (==1.12.1)
Requires-Dist: torchmetrics (==0.10.0)
Requires-Dist: tqdm (==4.64.1)
Requires-Dist: websocket-client (==1.4.2)
Requires-Dist: scikit-learn (~=1.2.1)
Requires-Dist: lightgbm (~=3.3.5)
Requires-Dist: mlflow (~=2.2.2)
